setup.py
flask_jade2underscore.egg-info/PKG-INFO
flask_jade2underscore.egg-info/SOURCES.txt
flask_jade2underscore.egg-info/dependency_links.txt
flask_jade2underscore.egg-info/namespace_packages.txt
flask_jade2underscore.egg-info/not-zip-safe
flask_jade2underscore.egg-info/requires.txt
flask_jade2underscore.egg-info/top_level.txt
flaskext/__init__.py
flaskext/jade2underscore.py