Metadata-Version: 1.0
Name: flask-jade2underscore
Version: 0.1
Summary: A small Flask extension adds suppot to Jade2Underscore templates compiler (used in Backbone) to Flask.
Home-page: https://github.com/weapp/flask-jade2underscore
Author: Manuel Albarran
Author-email: UNKNOWN
License: MIT
Platform: any
Classifier: Development Status :: 4 - Beta
Classifier: Environment :: Web Environment
Classifier: Intended Audience :: Developers
Classifier: License :: OSI Approved :: MIT License
Classifier: Operating System :: OS Independent
Classifier: Programming Language :: Python
Classifier: Topic :: Internet :: WWW/HTTP :: Dynamic Content
Classifier: Topic :: Software Development :: Libraries :: Python Modules
